extractor/__init__.py
extractor/checks.py
extractor/core.py
extractor/logger.py
extractor/main.py
extractor/render.py
pymetasnap-0.48.0.dist-info/LICENSE
pymetasnap-0.48.0.dist-info/METADATA
pymetasnap-0.48.0.dist-info/WHEEL
pymetasnap-0.48.0.dist-info/entry_points.txt
pymetasnap-0.48.0.dist-info/RECORD
