Metadata-Version: 2.3
Name: pymetasnap
Version: 0.48.0
Summary: This package allows you to scrape metadata from the Python Package Index
License: MIT
Author: cristian-rincon
Author-email: cristian.o.rincon.b@gmail.com
Requires-Python: >=3.8,<4.0
Classifier: License :: OSI Approved :: MIT License
Classifier: Programming Language :: Python :: 3
Classifier: Programming Language :: Python :: 3.8
Classifier: Programming Language :: Python :: 3.9
Classifier: Programming Language :: Python :: 3.10
Classifier: Programming Language :: Python :: 3.11
Classifier: Programming Language :: Python :: 3.12
Classifier: Programming Language :: Python :: 3.13
Requires-Dist: ghapi (>=1.0.4,<2.0.0)
Requires-Dist: loguru (>=0.7.0,<0.8.0)
Requires-Dist: openpyxl (>=3.1.2,<4.0.0)
Requires-Dist: pandas (>=2.0.2,<3.0.0)
Requires-Dist: requests (>=2.31.0,<3.0.0)
Requires-Dist: rich (>=13.4.1,<15.0.0)
Requires-Dist: shellingham (>=1.5.0.post1,<2.0.0)
Requires-Dist: toml (>=0.10.2,<0.11.0)
Requires-Dist: typer[all] (>=0.9,<0.17)
